diffSPH/__init__.py
diffSPH/boundary.py
diffSPH/compiler.py
diffSPH/dataLoader.py
diffSPH/enums.py
diffSPH/finiteDifference.py
diffSPH/ghost.py
diffSPH/gradientUtil.py
diffSPH/integration.py
diffSPH/io.py
diffSPH/jitTest.ipynb
diffSPH/kernelTest.ipynb
diffSPH/kernels.py
diffSPH/math.py
diffSPH/neighborhood.py
diffSPH/noise.py
diffSPH/operations.py
diffSPH/plotting.py
diffSPH/regions.py
diffSPH/rigidBody.py
diffSPH/sampling.py
diffSPH/schema.py
diffSPH/sdf.py
diffSPH/simple.py
diffSPH/sparse.py
diffSPH/test.py
diffSPH/util.py
diffSPH/cppSrc/common.h
diffSPH/cppSrc/cppWrapper.cpp
diffSPH/cppSrc/gradientOperations/gradientVector.h
diffSPH/cppSrc/gradientOperations/gradientVector_cpu.cpp
diffSPH/cppSrc/gradientOperations/gradientVector_cuda.cu
diffSPH/dataLoaderUtils/augment.py
diffSPH/dataLoaderUtils/batch.py
diffSPH/dataLoaderUtils/cuMathLoader.py
diffSPH/dataLoaderUtils/diffSPHLoader.py
diffSPH/dataLoaderUtils/fallback.py
diffSPH/dataLoaderUtils/lbench.py
diffSPH/dataLoaderUtils/loader.py
diffSPH/dataLoaderUtils/neighborhood.py
diffSPH/dataLoaderUtils/newFormatLoader.py
diffSPH/dataLoaderUtils/ops.py
diffSPH/dataLoaderUtils/plotting2.py
diffSPH/dataLoaderUtils/sampling.py
diffSPH/dataLoaderUtils/state.py
diffSPH/dataLoaderUtils/testcaseIILoader.py
diffSPH/dataLoaderUtils/util.py
diffSPH/integrationSchemes/butcher.py
diffSPH/integrationSchemes/euler.py
diffSPH/integrationSchemes/ruth.py
diffSPH/integrationSchemes/tvd.py
diffSPH/integrationSchemes/util.py
diffSPH/integrationSchemes/verlet.py
diffSPH/kernelFunctions/AdhesionKernel.py
diffSPH/kernelFunctions/B7.py
diffSPH/kernelFunctions/CohesionKernel.py
diffSPH/kernelFunctions/CubicSpline.py
diffSPH/kernelFunctions/Poly6.py
diffSPH/kernelFunctions/QuarticSpline.py
diffSPH/kernelFunctions/QuinticSpline.py
diffSPH/kernelFunctions/Spiky.py
diffSPH/kernelFunctions/ViscosityKernel.py
diffSPH/kernelFunctions/Wendland2.py
diffSPH/kernelFunctions/Wendland4.py
diffSPH/kernelFunctions/Wendland6.py
diffSPH/modules/CRKSPH.py
diffsph-0.2.1.dist-info/licenses/LICENSE
diffsph-0.2.1.dist-info/METADATA
diffsph-0.2.1.dist-info/WHEEL
diffsph-0.2.1.dist-info/top_level.txt
diffsph-0.2.1.dist-info/RECORD
