Metadata-Version: 2.4
Name: diffSPH
Version: 0.2.1
Summary: A Fully differentiable SPH Solver.
Author-email: Rene Winchenbach <contact@fluids.dev>
Maintainer-email: Rene Winchenbach <contact@fluids.dev>
License:                                  Apache License
Project-URL: Repository, https://github.com/tum-pbs/diffSPH
Project-URL: Issues, https://github.com/tum-pbs/diffSPH
Keywords: sph,radius,pytorch
Classifier: Development Status :: 4 - Beta
Classifier: Intended Audience :: Developers
Classifier: Programming Language :: Python :: 3
Classifier: License :: OSI Approved :: Apache Software License
Classifier: Operating System :: OS Independent
License-File: LICENSE
Requires-Dist: torch
Requires-Dist: numpy
Dynamic: license-file
